{
  "contract_version": "1.0.0",
  "request_id": "req_01JANALYZE",
  "trip_id": "trp_2aeb3d2e-17db-4ce7-91f2-f01f0a2b0d44",
  "itinerary": {
    "days": [
      {
        "date": "2026-04-02",
        "locations": [
          {
            "name": "Bodh Gaya",
            "district": "Gaya",
            "connectivity_zone": "urban_stable",
            "assumed_location_risk": "moderate"
          }
        ],
        "accommodation": "Monastery Road Guest House"
      }
    ],
    "meta": {
      "source": "pdf_upload"
    }
  }
}
